{"singlePage": [], "startSite": "", "filingNum": "", "onePageListNum": 15, "commentLabelColor": "#006b75", "yearColorList": ["#bc4c00", "#0969da", "#1f883d", "#A333D0"], "i18n": "CN", "themeMode": "manual", "dayTheme": "light", "nightTheme": "dark", "urlMode": "pinyin", "script": "", "style": "", "indexScript": "", "indexStyle": "", "bottomText": "", "showPostSource": 1, "iconList": {}, "UTC": 8, "rssSplit": "sentence", "exlink": {}, "title": "\u5c0f\u67ab\u7231\u5b66\u4e60", "subTitle": "\u5b66\u4e60\u5206\u4eab", "avatarUrl": "https://github.githubassets.com/favicons/favicon.svg", "GMEEK_VERSION": "last", "postListJson": {"P2": {"htmlDir": "docs/post/nv-xing-ren-zhi-te-ding-zong-jie.html", "labels": ["documentation"], "postTitle": "\u5973\u6027\u8ba4\u77e5\u7279\u5b9a\u603b\u7ed3", "postUrl": "post/nv-xing-ren-zhi-te-ding-zong-jie.html", "postSourceUrl": "https://github.com/olivefengsz/olivelovescience.github.io/issues/2", "commentNum": 0, "wordCount": 122, "description": "![\u5973\u6027\u8ba4\u77e5\u7279\u70b9](https://github.com/olivefengsz/olivelovescience.github.io/assets/8655791/dc950834-2f20-419d-8e18-ac455181d12c)\r\n\u3002", "top": 0, "createdAt": 1712322944, "style": "", "script": "", "ogImage": "https://github.githubassets.com/favicons/favicon.svg", "createdDate": "2024-04-05", "dateLabelColor": "#bc4c00"}, "P3": {"htmlDir": "docs/post/1\uff0c-gai-lv-lun-ji-chu-zhi-shi.html", "labels": ["documentation", "\u6982\u7387\u8bba"], "postTitle": "1\uff0c\u6982\u7387\u8bba\u57fa\u7840\u77e5\u8bc6", "postUrl": "post/1%EF%BC%8C-gai-lv-lun-ji-chu-zhi-shi.html", "postSourceUrl": "https://github.com/olivefengsz/olivelovescience.github.io/issues/3", "commentNum": 0, "wordCount": 127, "description": "![\u6982\u7387\u8bba\u57fa\u7840\u77e5\u8bc6](https://github.com/olivefengsz/olivelovescience.github.io/assets/8655791/c6e4d9a2-24a1-41ca-b78a-1c442d7cd35f)\r\n\r\n\r\n\u3002", "top": 0, "createdAt": 1714284939, "style": "", "script": "", "ogImage": "https://github.githubassets.com/favicons/favicon.svg", "createdDate": "2024-04-28", "dateLabelColor": "#bc4c00"}, "P4": {"htmlDir": "docs/post/\u300a-shu-ju-jie-gou-yu-suan-fa-zhi-mei-\u300b-zhi-fu-za-du.html", "labels": ["documentation", "\u6570\u636e\u7ed3\u6784\u4e0e\u7b97\u6cd5"], "postTitle": "\u300a\u6570\u636e\u7ed3\u6784\u4e0e\u7b97\u6cd5\u4e4b\u7f8e\u300b\u4e4b\u590d\u6742\u5ea6", "postUrl": "post/%E3%80%8A-shu-ju-jie-gou-yu-suan-fa-zhi-mei-%E3%80%8B-zhi-fu-za-du.html", "postSourceUrl": "https://github.com/olivefengsz/olivelovescience.github.io/issues/4", "commentNum": 0, "wordCount": 130, "description": "![\u300a\u6570\u636e\u7ed3\u6784\u4e0e\u7b97\u6cd5\u300b\u590d\u6742\u5ea6\u5206\u6790](https://github.com/olivefengsz/olivelovescience.github.io/assets/8655791/ac1a44ae-b344-4082-b828-ddf7ed981a50)\r\n\u3002", "top": 0, "createdAt": 1714301264, "style": "", "script": "", "ogImage": "https://github.githubassets.com/favicons/favicon.svg", "createdDate": "2024-04-28", "dateLabelColor": "#bc4c00"}, "P5": {"htmlDir": "docs/post/2, -sui-ji-bian-liang.html", "labels": ["documentation", "\u6982\u7387\u8bba"], "postTitle": "2, \u968f\u673a\u53d8\u91cf", "postUrl": "post/2%2C%20-sui-ji-bian-liang.html", "postSourceUrl": "https://github.com/olivefengsz/olivelovescience.github.io/issues/5", "commentNum": 0, "wordCount": 156, "description": "\r\n<img width='1506' alt='\u968f\u673a\u53d8\u91cf\u53ca\u5206\u5e03' src='https://github.com/olivefengsz/olivelovescience.github.io/assets/8655791/3f96b57d-d047-45ff-af58-676c21829227'>\r\n\r\n\r\n\u3002", "top": 0, "createdAt": 1714388552, "style": "", "script": "", "ogImage": "https://github.githubassets.com/favicons/favicon.svg", "createdDate": "2024-04-29", "dateLabelColor": "#bc4c00"}, "P6": {"htmlDir": "docs/post/3, -duo-wei-sui-ji-bian-liang.html", "labels": ["documentation", "\u6982\u7387\u8bba"], "postTitle": "3, \u591a\u7ef4\u968f\u673a\u53d8\u91cf", "postUrl": "post/3%2C%20-duo-wei-sui-ji-bian-liang.html", "postSourceUrl": "https://github.com/olivefengsz/olivelovescience.github.io/issues/6", "commentNum": 0, "wordCount": 125, "description": "![3  \u591a\u7ef4\u968f\u673a\u53d8\u91cf](https://github.com/olivefengsz/olivelovescience.github.io/assets/8655791/05664602-8059-41ac-b829-0d1ec4bda125)\r\n\u3002", "top": 0, "createdAt": 1714473487, "style": "", "script": "", "ogImage": "https://github.githubassets.com/favicons/favicon.svg", "createdDate": "2024-04-30", "dateLabelColor": "#bc4c00"}, "P7": {"htmlDir": "docs/post/4\uff0c-shu-zi-te-zheng.html", "labels": ["documentation", "\u6982\u7387\u8bba"], "postTitle": "4\uff0c\u6570\u5b57\u7279\u5f81", "postUrl": "post/4%EF%BC%8C-shu-zi-te-zheng.html", "postSourceUrl": "https://github.com/olivefengsz/olivelovescience.github.io/issues/7", "commentNum": 0, "wordCount": 147, "description": "<img width='1126' alt='\u6570\u5b57\u7279\u5f81' src='https://github.com/olivefengsz/olivelovescience.github.io/assets/8655791/53fc56a9-1749-48f9-9e87-763129a4b1e1'>\r\n\u3002", "top": 0, "createdAt": 1714663918, "style": "", "script": "", "ogImage": "https://github.githubassets.com/favicons/favicon.svg", "createdDate": "2024-05-02", "dateLabelColor": "#bc4c00"}, "P8": {"htmlDir": "docs/post/5\uff0c-da-shu-ding-lv.html", "labels": ["documentation", "\u6982\u7387\u8bba"], "postTitle": "5\uff0c\u5927\u6570\u5b9a\u5f8b", "postUrl": "post/5%EF%BC%8C-da-shu-ding-lv.html", "postSourceUrl": "https://github.com/olivefengsz/olivelovescience.github.io/issues/8", "commentNum": 0, "wordCount": 147, "description": "<img width='1395' alt='\u5927\u6570\u5b9a\u5f8b' src='https://github.com/olivefengsz/olivelovescience.github.io/assets/8655791/8f95e4a2-32f4-4890-9466-2c892b2d1789'>\r\n\u3002", "top": 0, "createdAt": 1714745599, "style": "", "script": "", "ogImage": "https://github.githubassets.com/favicons/favicon.svg", "createdDate": "2024-05-03", "dateLabelColor": "#bc4c00"}, "P9": {"htmlDir": "docs/post/6, -tong-ji-li-lun.html", "labels": ["documentation", "\u6982\u7387\u8bba"], "postTitle": "6, \u7edf\u8ba1\u7406\u8bba", "postUrl": "post/6%2C%20-tong-ji-li-lun.html", "postSourceUrl": "https://github.com/olivefengsz/olivelovescience.github.io/issues/9", "commentNum": 0, "wordCount": 122, "description": "![6\uff0c\u7edf\u8ba1\u5206\u5e03](https://github.com/olivefengsz/olivelovescience.github.io/assets/8655791/0c8f9789-d0a0-48c7-9355-8d44f0f8542d)\r\n\u3002", "top": 0, "createdAt": 1714917241, "style": "", "script": "", "ogImage": "https://github.githubassets.com/favicons/favicon.svg", "createdDate": "2024-05-05", "dateLabelColor": "#bc4c00"}, "P10": {"htmlDir": "docs/post/7\uff0c-can-shu-gu-ji.html", "labels": ["documentation", "\u6982\u7387\u8bba"], "postTitle": "7\uff0c\u53c2\u6570\u4f30\u8ba1", "postUrl": "post/7%EF%BC%8C-can-shu-gu-ji.html", "postSourceUrl": "https://github.com/olivefengsz/olivelovescience.github.io/issues/10", "commentNum": 0, "wordCount": 122, "description": "![7\uff0c\u53c2\u6570\u4f30\u8ba1](https://github.com/olivefengsz/olivelovescience.github.io/assets/8655791/dae769be-380e-4a42-9083-20d0552c1348)\r\n\u3002", "top": 0, "createdAt": 1715007929, "style": "", "script": "", "ogImage": "https://github.githubassets.com/favicons/favicon.svg", "createdDate": "2024-05-06", "dateLabelColor": "#bc4c00"}, "P11": {"htmlDir": "docs/post/8\uff0c-jia-she-jian-yan.html", "labels": ["documentation", "\u6982\u7387\u8bba"], "postTitle": "8\uff0c\u5047\u8bbe\u68c0\u9a8c", "postUrl": "post/8%EF%BC%8C-jia-she-jian-yan.html", "postSourceUrl": "https://github.com/olivefengsz/olivelovescience.github.io/issues/11", "commentNum": 0, "wordCount": 123, "description": "![8  \u5047\u8bbe\u68c0\u9a8c](https://github.com/olivefengsz/olivelovescience.github.io/assets/8655791/cddf5718-f3ac-47e4-b01e-c8428c41a47a)\r\n\u3002", "top": 0, "createdAt": 1715087733, "style": "", "script": "", "ogImage": "https://github.githubassets.com/favicons/favicon.svg", "createdDate": "2024-05-07", "dateLabelColor": "#bc4c00"}, "P12": {"htmlDir": "docs/post/tou-guo-jie-gou-kan-biao-da-xue-xi-bi-ji.html", "labels": ["documentation", "\u7ed3\u6784\u601d\u7ef4"], "postTitle": "\u900f\u8fc7\u7ed3\u6784\u770b\u8868\u8fbe\u5b66\u4e60\u7b14\u8bb0", "postUrl": "post/tou-guo-jie-gou-kan-biao-da-xue-xi-bi-ji.html", "postSourceUrl": "https://github.com/olivefengsz/olivelovescience.github.io/issues/12", "commentNum": 0, "wordCount": 123, "description": "![\u900f\u8fc7\u7ed3\u6784\u770b\u8868\u8fbe](https://github.com/olivefengsz/olivelovescience.github.io/assets/8655791/190892e7-889e-4758-93f2-a6579fb84710)\r\n\u3002", "top": 0, "createdAt": 1718972902, "style": "", "script": "", "ogImage": "https://github.githubassets.com/favicons/favicon.svg", "createdDate": "2024-06-21", "dateLabelColor": "#bc4c00"}}, "singeListJson": {}, "labelColorDict": {"bug": "#d73a4a", "documentation": "#0075ca", "duplicate": "#cfd3d7", "enhancement": "#a2eeef", "good first issue": "#7057ff", "help wanted": "#008672", "invalid": "#e4e669", "question": "#d876e3", "wontfix": "#ffffff", "\u6570\u636e\u7ed3\u6784\u4e0e\u7b97\u6cd5": "#d4c5f9", "\u6982\u7387\u8bba": "#e99695", "\u7ed3\u6784\u601d\u7ef4": "#d4c5f9"}, "displayTitle": "\u5c0f\u67ab\u7231\u5b66\u4e60", "faviconUrl": "https://github.githubassets.com/favicons/favicon.svg", "ogImage": "https://github.githubassets.com/favicons/favicon.svg", "homeUrl": "https://olivefengsz.github.io/olivelovescience.github.io", "prevUrl": "disabled", "nextUrl": "disabled"}